setup.py
plutus_models/__init__.py
plutus_models.egg-info/PKG-INFO
plutus_models.egg-info/SOURCES.txt
plutus_models.egg-info/dependency_links.txt
plutus_models.egg-info/top_level.txt
plutus_models/tortoise_models/__init__.py
plutus_models/tortoise_models/action.py
plutus_models/tortoise_models/block.py
plutus_models/tortoise_models/bot.py
plutus_models/tortoise_models/chat_member.py
plutus_models/tortoise_models/chats.py
plutus_models/tortoise_models/dialogue.py
plutus_models/tortoise_models/edited_message.py
plutus_models/tortoise_models/event.py
plutus_models/tortoise_models/file_model.py
plutus_models/tortoise_models/filter.py
plutus_models/tortoise_models/frozen_event.py
plutus_models/tortoise_models/message_model.py
plutus_models/tortoise_models/mind.py
plutus_models/tortoise_models/none_object.py
plutus_models/tortoise_models/postback.py
plutus_models/tortoise_models/token_model.py
plutus_models/tortoise_models/user.py
plutus_models/tortoise_models/user_events.py
plutus_models/tortoise_models/var.py
plutus_models/tortoise_models/actions/__init__.py
plutus_models/tortoise_models/actions/animation_message.py
plutus_models/tortoise_models/actions/approve_request.py
plutus_models/tortoise_models/actions/audio_message.py
plutus_models/tortoise_models/actions/base.py
plutus_models/tortoise_models/actions/chat_action.py
plutus_models/tortoise_models/actions/document_message.py
plutus_models/tortoise_models/actions/http_request_action.py
plutus_models/tortoise_models/actions/media_group_message.py
plutus_models/tortoise_models/actions/photo_message.py
plutus_models/tortoise_models/actions/text_message.py
plutus_models/tortoise_models/actions/video_message.py
plutus_models/tortoise_models/actions/video_note_message.py
plutus_models/tortoise_models/actions/voice_message.py
plutus_models/tortoise_models/buttons/__init__.py
plutus_models/tortoise_models/buttons/inline_button.py
plutus_models/tortoise_models/buttons/reply_button.py
plutus_models/tortoise_models/spammer/__init__.py
plutus_models/tortoise_models/spammer/group_bots.py
plutus_models/tortoise_models/spammer/spammer.py
