Metadata-Version: 2.1
Name: plutus-models
Version: 0.1.9
Summary: models for plutus app
Classifier: Programming Language :: Python :: 3.11
Classifier: License :: OSI Approved :: MIT License
Classifier: Operating System :: OS Independent
Requires-Python: >=3.6
